faker_zhcn/__init__.py
faker_zhcn/example.py
faker_zhcn-0.0.3.dist-info/LICENSE
faker_zhcn-0.0.3.dist-info/METADATA
faker_zhcn-0.0.3.dist-info/WHEEL
faker_zhcn-0.0.3.dist-info/top_level.txt
faker_zhcn-0.0.3.dist-info/RECORD
